{
  "tasks": [
    {
      "text": "Tender cake",
      "day": "04/23/2021",
      "reminder": true,
      "id": 2
    },
    {
      "text": "How many hours will I have to spent on this project?",
      "day": "05/01/2021",
      "reminder": true,
      "id": 3
    },
    {
      "text": "wecwec",
      "day": "cew",
      "reminder": true,
      "id": 5
    },
    {
      "text": "I bought a new mouse MX 3 Logitech",
      "day": "04/17/2021",
      "reminder": false,
      "id": 6
    },
    {
      "text": "fsefsef",
      "day": "wfewef",
      "reminder": false,
      "id": 7
    }
  ]
}